README.md
setup.py
pulumiverse_aquasec/__init__.py
pulumiverse_aquasec/_inputs.py
pulumiverse_aquasec/_utilities.py
pulumiverse_aquasec/acknowledge.py
pulumiverse_aquasec/application_scope.py
pulumiverse_aquasec/aqua_label.py
pulumiverse_aquasec/container_runtime_policy.py
pulumiverse_aquasec/enforcer_groups.py
pulumiverse_aquasec/firewall_policy.py
pulumiverse_aquasec/function_assurance_policy.py
pulumiverse_aquasec/function_runtime_policy.py
pulumiverse_aquasec/get_acknowledges.py
pulumiverse_aquasec/get_application_scope.py
pulumiverse_aquasec/get_aqua_labels.py
pulumiverse_aquasec/get_container_runtime_policy.py
pulumiverse_aquasec/get_enforcer_groups.py
pulumiverse_aquasec/get_firewall_policy.py
pulumiverse_aquasec/get_function_assurance_policy.py
pulumiverse_aquasec/get_function_runtime_policy.py
pulumiverse_aquasec/get_gateways.py
pulumiverse_aquasec/get_groups.py
pulumiverse_aquasec/get_host_assurance_policy.py
pulumiverse_aquasec/get_host_runtime_policy.py
pulumiverse_aquasec/get_image.py
pulumiverse_aquasec/get_image_assurance_policy.py
pulumiverse_aquasec/get_integration_registries.py
pulumiverse_aquasec/get_integration_registry.py
pulumiverse_aquasec/get_integration_state.py
pulumiverse_aquasec/get_kubernetes_assurance_policy.py
pulumiverse_aquasec/get_notifications.py
pulumiverse_aquasec/get_permissions_sets.py
pulumiverse_aquasec/get_roles.py
pulumiverse_aquasec/get_roles_mapping.py
pulumiverse_aquasec/get_roles_mapping_saas.py
pulumiverse_aquasec/get_service.py
pulumiverse_aquasec/get_users.py
pulumiverse_aquasec/get_users_saas.py
pulumiverse_aquasec/group.py
pulumiverse_aquasec/host_assurance_policy.py
pulumiverse_aquasec/host_runtime_policy.py
pulumiverse_aquasec/image.py
pulumiverse_aquasec/image_assurance_policy.py
pulumiverse_aquasec/integration_registry.py
pulumiverse_aquasec/kubernetes_assurance_policy.py
pulumiverse_aquasec/notification.py
pulumiverse_aquasec/notification_slack.py
pulumiverse_aquasec/outputs.py
pulumiverse_aquasec.egg-info/PKG-INFO
pulumiverse_aquasec.egg-info/SOURCES.txt
pulumiverse_aquasec.egg-info/dependency_links.txt
pulumiverse_aquasec.egg-info/not-zip-safe
pulumiverse_aquasec.egg-info/requires.txt
pulumiverse_aquasec.egg-info/top_level.txt
