Metadata-Version: 2.1
Name: pulumiverse-aquasec
Version: 0.8.29
Summary: A Pulumi package for creating and managing Aquasec cloud resources.
Home-page: https://www.pulumi.com
License: Apache-2.0
Project-URL: Repository, https://github.com/pulumiverse/pulumi-aquasec
Keywords: pulumi aquasec category/utility
Platform: UNKNOWN
Requires-Python: >=3.8
